multipla.py
multipla-0.3.3.dist-info/RECORD
multipla-0.3.3.dist-info/WHEEL
multipla-0.3.3.dist-info/metadata.json
multipla-0.3.3.dist-info/DESCRIPTION.rst
multipla-0.3.3.dist-info/METADATA
multipla-0.3.3.dist-info/top_level.txt
