Metadata-Version: 2.0
Name: multipla
Version: 0.3.3
Summary: Plugin handling system
